dsame3_simple/defs.py
dsame3_simple/dsame.py
dsame3_simple-0.0.3.dist-info/LICENSE
dsame3_simple-0.0.3.dist-info/METADATA
dsame3_simple-0.0.3.dist-info/WHEEL
dsame3_simple-0.0.3.dist-info/entry_points.txt
dsame3_simple-0.0.3.dist-info/top_level.txt
dsame3_simple-0.0.3.dist-info/RECORD
