Metadata-Version: 2.1
Name: dsame3_simple
Version: 0.0.3
Summary: Simplified version of dsame3 to decode EAS SAME messages to readable text.
Author: Joseph W. Metcalf, James Kitchens, Matthew R. McDougal
Author-email: "Matthew R. McDougal" <ka0s@arrl.net>
Project-URL: Homepage, https://github.com/ars-ka0s/dsame3_simple
Project-URL: Bug Tracker, https://github.com/ars-ka0s/dsame3_simple/issues
Classifier: Programming Language :: Python :: 3
Classifier: Development Status :: 3 - Alpha
Classifier: Intended Audience :: Developers
Classifier: License :: OSI Approved :: BSD License
Classifier: Operating System :: OS Independent
Classifier: Topic :: Communications :: Ham Radio
Requires-Python: >=3.8
License-File: LICENSE
